[

    {
        "src": "/static/2560px-Paul_Cézanne,_Mont_Sainte-Victoire.jpeg",
        "alt": "Mont Sainte-Victoire"

    },
    {
        "src": "/static/mill.jpeg",
        "alt":  "Coming from the mill"
    },   
    {
        "src": "/static/La_Corniche_near_Monaco.jpeg",
        "alt":  "La Corniche near Monaco"

    },  
    {
        "src": "/static/Pierre-Auguste_Renoir_-_Luncheon_of_the_Boating_Party_-_Google_Art_Project.jpeg",
        "alt": "Luncheon of the Boating Party"
    },   
    {
        "src": "/static/report%20me%20all%20well.jpeg",
        "alt": "Report me all well"
    },
    {
        "src": "/static//Eug%C3%A8ne_Louis_Lami_-_Opening_of_the_Great_Exhibition%2C_1_May_1851_-_Google_Art_Project.jpeg",
        "alt": "Opening of the Great Exhibition"
    },
    {
        "src": "/static/Jakob_Alt_-_View_from_the_Artist's_Studio_in_Alservorstadt_toward_Dornbach,_1836_-_Google_Art_Project.jpeg", 
        "alt": "View from the Artist's Studio in Alservorstadt toward Dornbach"
    },
    {
        "src": "/static/olive.jpg",
        "alt": "Olive Trees, Van Gogh"
    },
    {
        "src": "/static/starry.jpeg",
        "alt": "Starry Night"
    },
    {
        "src": "/static/almond.jpeg",
        "alt": "Almond Blossom, Van Gogh"
    },
    {
        "src": "/static/baroque.jpeg",
        "alt": "View through a Baroque Colonnade into a Garden"
    }
   
]